paragres/__init__.py
paragres/cli.py
paragres/command.py
paragres-0.6.3.dist-info/LICENSE.txt
paragres-0.6.3.dist-info/METADATA
paragres-0.6.3.dist-info/WHEEL
paragres-0.6.3.dist-info/entry_points.txt
paragres-0.6.3.dist-info/top_level.txt
paragres-0.6.3.dist-info/RECORD
