Metadata-Version: 2.1
Name: paragres
Version: 0.6.3
Summary: Utility for synchronizing parallel PostgreSQL databases on Heroku, local, and remote servers
Home-page: https://github.com/jessamynsmith/paragres
Author: Jessamyn Smith
Author-email: jessamyn.smith@gmail.com
License: MIT
Download-URL: https://github.com/jessamynsmith/paragres/archive/v0.6.3.tar.gz
Keywords: postgresql,postgres,psql,pgbackups,database,heroku
Platform: UNKNOWN
Classifier: Development Status :: 4 - Beta
Classifier: Environment :: Console
Classifier: Intended Audience :: Developers
Classifier: Programming Language :: Python
Classifier: Programming Language :: Python :: 2.7
Classifier: Programming Language :: Python :: 3.3
Classifier: Programming Language :: Python :: 3.4
Classifier: Programming Language :: Python :: 3.5
Classifier: License :: OSI Approved :: MIT License
Classifier: Topic :: Software Development
Classifier: Topic :: Utilities
